_jpegtran.pyd
jpegtran/jpegtran.cdef
jpegtran/jpegtran_build.py
jpegtran/lib.py
jpegtran/transform.py
jpegtran/__init__.py
jpegtran_cffi_wheels-0.5.3.dev0.data/platlib/.load-order-jpegtran_cffi_wheels-0.5.3.dev0
jpegtran_cffi_wheels-0.5.3.dev0.data/platlib/jpeg62-05f0a3c8422fdf2f8a1f93e0b6d47384.dll
jpegtran_cffi_wheels-0.5.3.dev0.data/platlib/turbojpeg-97e457425aa7d16261ce50ca6384a8d2.dll
jpegtran_cffi_wheels-0.5.3.dev0.dist-info/DELVEWHEEL
jpegtran_cffi_wheels-0.5.3.dev0.dist-info/LICENSE
jpegtran_cffi_wheels-0.5.3.dev0.dist-info/LICENSE-epeg
jpegtran_cffi_wheels-0.5.3.dev0.dist-info/LICENSE-jpeglib
jpegtran_cffi_wheels-0.5.3.dev0.dist-info/METADATA
jpegtran_cffi_wheels-0.5.3.dev0.dist-info/RECORD
jpegtran_cffi_wheels-0.5.3.dev0.dist-info/top_level.txt
jpegtran_cffi_wheels-0.5.3.dev0.dist-info/WHEEL
