Metadata-Version: 2.1
Name: jpegtran-cffi-wheels
Version: 0.5.3.dev0
Summary: Extremly fast, (mostly) lossless JPEG transformations
Home-page: http://github.com/jbaiter/jpegtran-cffi.git
Author: Johannes Baiter
Author-email: johannes.baiter@gmail.com
License: MIT
License-File: LICENSE
License-File: LICENSE-epeg
License-File: LICENSE-jpeglib
Requires-Dist: cffi (>=1.0)
